pcs_annotator/Annotator.py
pcs_annotator/LLM.py
pcs_annotator/PCS.py
pcs_annotator/TextMutator.py
pcs_annotator/Tools.py
pcs_annotator/__init__.py
pcs_annotator-0.2.3.dist-info/METADATA
pcs_annotator-0.2.3.dist-info/WHEEL
pcs_annotator-0.2.3.dist-info/licenses/LICENSE
pcs_annotator-0.2.3.dist-info/RECORD
